wqgdb/__init__.py
wqgdb/common.py
wqgdb/dfs.py
wqgdb/find.py
wqgdb/heap.py
wqgdb/ipc.py
wqgdb/kv.py
wqgdb/log.py
wqgdb/pm.py
wqgdb/queue.py
wqgdb/rpc.py
wqgdb/section.py
wqgdb/stack.py
wqgdb/task.py
wqgdb/timer.py
wqgdb/trace.py
wqgdb/usage.py
wqgdb/wdt.py
wqgdb-1.0.2.dist-info/METADATA
wqgdb-1.0.2.dist-info/WHEEL
wqgdb-1.0.2.dist-info/top_level.txt
wqgdb-1.0.2.dist-info/RECORD
